{"id": 496, "source": "pestle", "course": "AA", "level": "HL", "paper": "3", "year": "2018", "session": "18N", "subtopic": "ahl-5-13-limits-and-lhopitals", "title": "18N.3.AHL.TZ0.HCA_2", "topic_id": "5", "source_url": "https://pestle.pages.dev/app/", "question_html": "<div class=\"question\" style=\"padding-left: 20px; padding-right: 20px;\">\n<p>Use L’Hôpital’s rule to determine the value of</p>\n<p><span class=\"mjpage mjpage__block\"><math alttext=\"\\mathop {{\\text{lim}}}\\limits_{x \\to 0} \\left( {\\frac{{{{\\text{e}}^{ - 3x}}^{^2} + 3\\,{\\text{cos}}\\left( {2x} \\right) - 4}}{{3{x^2}}}} \\right)\" display=\"block\" xmlns=\"http://www.w3.org/1998/Math/MathML\">\n<munder>\n<mrow>\n<mrow>\n<mtext>lim</mtext>\n</mrow>\n</mrow>\n<mrow>\n<mi>x</mi>\n<mo stretchy=\"false\">→</mo>\n<mn>0</mn>\n</mrow>\n</munder>\n<mo>⁡</mo>\n<mrow>\n<mo>(</mo>\n<mrow>\n<mfrac>\n<mrow>\n<msup>\n<mrow>\n<msup>\n<mrow>\n<mtext>e</mtext>\n</mrow>\n<mrow>\n<mo>−</mo>\n<mn>3</mn>\n<mi>x</mi>\n</mrow>\n</msup>\n</mrow>\n<mrow>\n<msup>\n<mi></mi>\n<mn>2</mn>\n</msup>\n</mrow>\n</msup>\n<mo>+</mo>\n<mn>3</mn>\n<mspace width=\"thinmathspace\"></mspace>\n<mrow>\n<mtext>cos</mtext>\n</mrow>\n<mrow>\n<mo>(</mo>\n<mrow>\n<mn>2</mn>\n<mi>x</mi>\n</mrow>\n<mo>)</mo>\n</mrow>\n<mo>−</mo>\n<mn>4</mn>\n</mrow>\n<mrow>\n<mn>3</mn>\n<mrow>\n<msup>\n<mi>x</mi>\n<mn>2</mn>\n</msup>\n</mrow>\n</mrow>\n</mfrac>\n</mrow>\n<mo>)</mo>\n</mrow>\n</math></span></p>\n<div class=\"marks\">[5]</div>\n<div class=\"question_part_label\">a.</div>\n</div><div class=\"question\" style=\"padding-left: 20px; padding-right: 20px;\">\n<p>Hence find <span class=\"mjpage\"><math alttext=\"\\mathop {{\\text{lim}}}\\limits_{x \\to 0} \\left( {\\frac{{\\int_0^x {\\left( {{{\\text{e}}^{ - 3t}}^{^2} + 3\\,{\\text{cos}}\\left( {2t} \\right) - 4} \\right)} \\,{\\text{d}}t}}{{\\int_0^x {3{t^2}} \\,{\\text{d}}t}}} \\right)\" xmlns=\"http://www.w3.org/1998/Math/MathML\">\n<munder>\n<mrow>\n<mrow>\n<mtext>lim</mtext>\n</mrow>\n</mrow>\n<mrow>\n<mi>x</mi>\n<mo stretchy=\"false\">→</mo>\n<mn>0</mn>\n</mrow>\n</munder>\n<mo>⁡</mo>\n<mrow>\n<mo>(</mo>\n<mrow>\n<mfrac>\n<mrow>\n<msubsup>\n<mo>∫</mo>\n<mn>0</mn>\n<mi>x</mi>\n</msubsup>\n<mrow>\n<mrow>\n<mo>(</mo>\n<mrow>\n<msup>\n<mrow>\n<msup>\n<mrow>\n<mtext>e</mtext>\n</mrow>\n<mrow>\n<mo>−</mo>\n<mn>3</mn>\n<mi>t</mi>\n</mrow>\n</msup>\n</mrow>\n<mrow>\n<msup>\n<mi></mi>\n<mn>2</mn>\n</msup>\n</mrow>\n</msup>\n<mo>+</mo>\n<mn>3</mn>\n<mspace width=\"thinmathspace\"></mspace>\n<mrow>\n<mtext>cos</mtext>\n</mrow>\n<mrow>\n<mo>(</mo>\n<mrow>\n<mn>2</mn>\n<mi>t</mi>\n</mrow>\n<mo>)</mo>\n</mrow>\n<mo>−</mo>\n<mn>4</mn>\n</mrow>\n<mo>)</mo>\n</mrow>\n</mrow>\n<mspace width=\"thinmathspace\"></mspace>\n<mrow>\n<mtext>d</mtext>\n</mrow>\n<mi>t</mi>\n</mrow>\n<mrow>\n<msubsup>\n<mo>∫</mo>\n<mn>0</mn>\n<mi>x</mi>\n</msubsup>\n<mrow>\n<mn>3</mn>\n<mrow>\n<msup>\n<mi>t</mi>\n<mn>2</mn>\n</msup>\n</mrow>\n</mrow>\n<mspace width=\"thinmathspace\"></mspace>\n<mrow>\n<mtext>d</mtext>\n</mrow>\n<mi>t</mi>\n</mrow>\n</mfrac>\n</mrow>\n<mo>)</mo>\n</mrow>\n</math></span>.</p>\n<div class=\"marks\">[3]</div>\n<div class=\"question_part_label\">b.</div>\n</div>", "solution_html": "<div class=\"question\" style=\"padding-left: 20px;\">\n<p style=\"color: #999;font-size: 90%;font-style: italic;\">* This question is from an exam for a previous syllabus, and may contain minor differences in marking or structure.</p><p><span class=\"mjpage\"><math alttext=\"\\mathop {{\\text{lim}}}\\limits_{x \\to 0} \\frac{{{{\\text{e}}^{ - 3x}}^{^2} + 3\\,{\\text{cos}}\\,2x - 4}}{{3{x^2}}} = \\left( {\\begin{array}{*{20}{c}}  0 \\\\   0  \\end{array}} \\right)\" xmlns=\"http://www.w3.org/1998/Math/MathML\">\n<munder>\n<mrow>\n<mrow>\n<mtext>lim</mtext>\n</mrow>\n</mrow>\n<mrow>\n<mi>x</mi>\n<mo stretchy=\"false\">→</mo>\n<mn>0</mn>\n</mrow>\n</munder>\n<mo>⁡</mo>\n<mfrac>\n<mrow>\n<msup>\n<mrow>\n<msup>\n<mrow>\n<mtext>e</mtext>\n</mrow>\n<mrow>\n<mo>−</mo>\n<mn>3</mn>\n<mi>x</mi>\n</mrow>\n</msup>\n</mrow>\n<mrow>\n<msup>\n<mi></mi>\n<mn>2</mn>\n</msup>\n</mrow>\n</msup>\n<mo>+</mo>\n<mn>3</mn>\n<mspace width=\"thinmathspace\"></mspace>\n<mrow>\n<mtext>cos</mtext>\n</mrow>\n<mspace width=\"thinmathspace\"></mspace>\n<mn>2</mn>\n<mi>x</mi>\n<mo>−</mo>\n<mn>4</mn>\n</mrow>\n<mrow>\n<mn>3</mn>\n<mrow>\n<msup>\n<mi>x</mi>\n<mn>2</mn>\n</msup>\n</mrow>\n</mrow>\n</mfrac>\n<mo>=</mo>\n<mrow>\n<mo>(</mo>\n<mrow>\n<mtable columnspacing=\"1em\" rowspacing=\"4pt\">\n<mtr>\n<mtd>\n<mn>0</mn>\n</mtd>\n</mtr>\n<mtr>\n<mtd>\n<mn>0</mn>\n</mtd>\n</mtr>\n</mtable>\n</mrow>\n<mo>)</mo>\n</mrow>\n</math></span></p>\n<p><span class=\"mjpage\"><math alttext=\" = \\mathop {{\\text{lim}}}\\limits_{x \\to 0} \\frac{{ - {\\text{6}}x{{\\text{e}}^{ - 3x}}^{^2} - 6\\,{\\text{sin}}\\,2x}}{{6x}} = \\left( {\\begin{array}{*{20}{c}}  0 \\\\   0  \\end{array}} \\right)\" xmlns=\"http://www.w3.org/1998/Math/MathML\">\n<mo>=</mo>\n<munder>\n<mrow>\n<mrow>\n<mtext>lim</mtext>\n</mrow>\n</mrow>\n<mrow>\n<mi>x</mi>\n<mo stretchy=\"false\">→</mo>\n<mn>0</mn>\n</mrow>\n</munder>\n<mo>⁡</mo>\n<mfrac>\n<mrow>\n<mo>−</mo>\n<mrow>\n<mtext>6</mtext>\n</mrow>\n<mi>x</mi>\n<msup>\n<mrow>\n<msup>\n<mrow>\n<mtext>e</mtext>\n</mrow>\n<mrow>\n<mo>−</mo>\n<mn>3</mn>\n<mi>x</mi>\n</mrow>\n</msup>\n</mrow>\n<mrow>\n<msup>\n<mi></mi>\n<mn>2</mn>\n</msup>\n</mrow>\n</msup>\n<mo>−</mo>\n<mn>6</mn>\n<mspace width=\"thinmathspace\"></mspace>\n<mrow>\n<mtext>sin</mtext>\n</mrow>\n<mspace width=\"thinmathspace\"></mspace>\n<mn>2</mn>\n<mi>x</mi>\n</mrow>\n<mrow>\n<mn>6</mn>\n<mi>x</mi>\n</mrow>\n</mfrac>\n<mo>=</mo>\n<mrow>\n<mo>(</mo>\n<mrow>\n<mtable columnspacing=\"1em\" rowspacing=\"4pt\">\n<mtr>\n<mtd>\n<mn>0</mn>\n</mtd>\n</mtr>\n<mtr>\n<mtd>\n<mn>0</mn>\n</mtd>\n</mtr>\n</mtable>\n</mrow>\n<mo>)</mo>\n</mrow>\n</math></span>      <em><strong> M1A1A1</strong></em></p>\n<p><span class=\"mjpage\"><math alttext=\" = \\mathop {{\\text{lim}}}\\limits_{x \\to 0} \\frac{{ - {\\text{6}}{{\\text{e}}^{ - 3x}}^{^2} + 36{x^2}{{\\text{e}}^{ - 3x}}^{^2} - 12\\,{\\text{cos}}\\,2x}}{6}\" xmlns=\"http://www.w3.org/1998/Math/MathML\">\n<mo>=</mo>\n<munder>\n<mrow>\n<mrow>\n<mtext>lim</mtext>\n</mrow>\n</mrow>\n<mrow>\n<mi>x</mi>\n<mo stretchy=\"false\">→</mo>\n<mn>0</mn>\n</mrow>\n</munder>\n<mo>⁡</mo>\n<mfrac>\n<mrow>\n<mo>−</mo>\n<mrow>\n<mtext>6</mtext>\n</mrow>\n<msup>\n<mrow>\n<msup>\n<mrow>\n<mtext>e</mtext>\n</mrow>\n<mrow>\n<mo>−</mo>\n<mn>3</mn>\n<mi>x</mi>\n</mrow>\n</msup>\n</mrow>\n<mrow>\n<msup>\n<mi></mi>\n<mn>2</mn>\n</msup>\n</mrow>\n</msup>\n<mo>+</mo>\n<mn>36</mn>\n<mrow>\n<msup>\n<mi>x</mi>\n<mn>2</mn>\n</msup>\n</mrow>\n<msup>\n<mrow>\n<msup>\n<mrow>\n<mtext>e</mtext>\n</mrow>\n<mrow>\n<mo>−</mo>\n<mn>3</mn>\n<mi>x</mi>\n</mrow>\n</msup>\n</mrow>\n<mrow>\n<msup>\n<mi></mi>\n<mn>2</mn>\n</msup>\n</mrow>\n</msup>\n<mo>−</mo>\n<mn>12</mn>\n<mspace width=\"thinmathspace\"></mspace>\n<mrow>\n<mtext>cos</mtext>\n</mrow>\n<mspace width=\"thinmathspace\"></mspace>\n<mn>2</mn>\n<mi>x</mi>\n</mrow>\n<mn>6</mn>\n</mfrac>\n</math></span>      <em><strong>A1</strong></em></p>\n<p>= −3       <em><strong>A1</strong></em></p>\n<p> </p>\n<p><em><strong>[5 marks]</strong></em></p>\n<div class=\"question_part_label\">a.</div>\n</div><div class=\"question\" style=\"padding-left: 20px;\">\n<p><span class=\"mjpage\"><math alttext=\"\\mathop {{\\text{lim}}}\\limits_{x \\to 0} \\left( {\\frac{{\\int_0^x {\\left( {{{\\text{e}}^{ - 3t}}^{^2} + 3\\,{\\text{cos}}\\,2t - 4} \\right)} \\,{\\text{d}}t}}{{\\int_0^x {3{t^2}} \\,{\\text{d}}t}}} \\right)\" xmlns=\"http://www.w3.org/1998/Math/MathML\">\n<munder>\n<mrow>\n<mrow>\n<mtext>lim</mtext>\n</mrow>\n</mrow>\n<mrow>\n<mi>x</mi>\n<mo stretchy=\"false\">→</mo>\n<mn>0</mn>\n</mrow>\n</munder>\n<mo>⁡</mo>\n<mrow>\n<mo>(</mo>\n<mrow>\n<mfrac>\n<mrow>\n<msubsup>\n<mo>∫</mo>\n<mn>0</mn>\n<mi>x</mi>\n</msubsup>\n<mrow>\n<mrow>\n<mo>(</mo>\n<mrow>\n<msup>\n<mrow>\n<msup>\n<mrow>\n<mtext>e</mtext>\n</mrow>\n<mrow>\n<mo>−</mo>\n<mn>3</mn>\n<mi>t</mi>\n</mrow>\n</msup>\n</mrow>\n<mrow>\n<msup>\n<mi></mi>\n<mn>2</mn>\n</msup>\n</mrow>\n</msup>\n<mo>+</mo>\n<mn>3</mn>\n<mspace width=\"thinmathspace\"></mspace>\n<mrow>\n<mtext>cos</mtext>\n</mrow>\n<mspace width=\"thinmathspace\"></mspace>\n<mn>2</mn>\n<mi>t</mi>\n<mo>−</mo>\n<mn>4</mn>\n</mrow>\n<mo>)</mo>\n</mrow>\n</mrow>\n<mspace width=\"thinmathspace\"></mspace>\n<mrow>\n<mtext>d</mtext>\n</mrow>\n<mi>t</mi>\n</mrow>\n<mrow>\n<msubsup>\n<mo>∫</mo>\n<mn>0</mn>\n<mi>x</mi>\n</msubsup>\n<mrow>\n<mn>3</mn>\n<mrow>\n<msup>\n<mi>t</mi>\n<mn>2</mn>\n</msup>\n</mrow>\n</mrow>\n<mspace width=\"thinmathspace\"></mspace>\n<mrow>\n<mtext>d</mtext>\n</mrow>\n<mi>t</mi>\n</mrow>\n</mfrac>\n</mrow>\n<mo>)</mo>\n</mrow>\n</math></span> is of the form <span class=\"mjpage\"><math alttext=\"\\frac{0}{0}\" xmlns=\"http://www.w3.org/1998/Math/MathML\">\n<mfrac>\n<mn>0</mn>\n<mn>0</mn>\n</mfrac>\n</math></span></p>\n<p>applying l’Hôpital´s rule        <em><strong>(M1)</strong></em></p>\n<p><span class=\"mjpage\"><math alttext=\"\\mathop {{\\text{lim}}}\\limits_{x \\to 0} \\frac{{{{\\text{e}}^{ - 3x}}^{^2} + 3\\,{\\text{cos}}\\,2x - 4}}{{3{x^2}}}\" xmlns=\"http://www.w3.org/1998/Math/MathML\">\n<munder>\n<mrow>\n<mrow>\n<mtext>lim</mtext>\n</mrow>\n</mrow>\n<mrow>\n<mi>x</mi>\n<mo stretchy=\"false\">→</mo>\n<mn>0</mn>\n</mrow>\n</munder>\n<mo>⁡</mo>\n<mfrac>\n<mrow>\n<msup>\n<mrow>\n<msup>\n<mrow>\n<mtext>e</mtext>\n</mrow>\n<mrow>\n<mo>−</mo>\n<mn>3</mn>\n<mi>x</mi>\n</mrow>\n</msup>\n</mrow>\n<mrow>\n<msup>\n<mi></mi>\n<mn>2</mn>\n</msup>\n</mrow>\n</msup>\n<mo>+</mo>\n<mn>3</mn>\n<mspace width=\"thinmathspace\"></mspace>\n<mrow>\n<mtext>cos</mtext>\n</mrow>\n<mspace width=\"thinmathspace\"></mspace>\n<mn>2</mn>\n<mi>x</mi>\n<mo>−</mo>\n<mn>4</mn>\n</mrow>\n<mrow>\n<mn>3</mn>\n<mrow>\n<msup>\n<mi>x</mi>\n<mn>2</mn>\n</msup>\n</mrow>\n</mrow>\n</mfrac>\n</math></span>       <em><strong>(A1)</strong></em></p>\n<p>= −3        <em><strong>A1</strong></em> </p>\n<p> </p>\n<p><em><strong>[3 marks]</strong></em></p>\n<div class=\"question_part_label\">b.</div>\n</div>", "examiners_html": "<div class=\"question\" style=\"padding-left: 20px;\">\n[N/A]\n<div class=\"question_part_label\">a.</div>\n</div><div class=\"question\" style=\"padding-left: 20px;\">\n[N/A]\n<div class=\"question_part_label\">b.</div>\n</div>"}