{"id": 831, "source": "pestle", "subject": "maths", "course": "AA", "level": "SL", "paper": "1", "year": "2022", "session": "22M", "subtopic": "sl-5-4-tangents-and-normal", "title": "22M.1.SL.TZ1.5", "topic_id": "5", "source_url": "https://pestle.pages.dev/app/", "question_html": "<div class=\"question\">\n<p>Consider the curve with equation <math xmlns=\"http://www.w3.org/1998/Math/MathML\"><mi>y</mi><mo>=</mo><mo>(</mo><mn>2</mn><mi>x</mi><mo>-</mo><mn>1</mn><mo>)</mo><msup><mtext>e</mtext><mrow><mi>k</mi><mi>x</mi></mrow></msup></math>, where <math xmlns=\"http://www.w3.org/1998/Math/MathML\"><mi>x</mi><mo>∈</mo><mi mathvariant=\"normal\">ℝ</mi></math> and <math xmlns=\"http://www.w3.org/1998/Math/MathML\"><mi>k</mi><mo>∈</mo><mi mathvariant=\"normal\">ℚ</mi></math>.</p>\n<p>The tangent to the curve at the point where <math xmlns=\"http://www.w3.org/1998/Math/MathML\"><mi>x</mi><mo>=</mo><mn>1</mn></math> is parallel to the line <math xmlns=\"http://www.w3.org/1998/Math/MathML\"><mi>y</mi><mo>=</mo><mn>5</mn><msup><mtext>e</mtext><mi>k</mi></msup><mi>x</mi></math>.</p>\n<p>Find the value of <math xmlns=\"http://www.w3.org/1998/Math/MathML\"><mi>k</mi></math>.</p>\n</div>", "solution_html": "<div class=\"question\">\n<p>evidence of using product rule           <em><strong>(M1)</strong></em></p>\n<p><math xmlns=\"http://www.w3.org/1998/Math/MathML\"><mfrac><mrow><mo>d</mo><mi>y</mi></mrow><mrow><mo>d</mo><mi>x</mi></mrow></mfrac><mo>=</mo><mfenced><mrow><mn>2</mn><mi>x</mi><mo>-</mo><mn>1</mn></mrow></mfenced><mo>×</mo><mfenced><mrow><mi>k</mi><msup><mtext>e</mtext><mrow><mi>k</mi><mi>x</mi></mrow></msup></mrow></mfenced><mo>+</mo><mn>2</mn><mo>×</mo><msup><mtext>e</mtext><mrow><mi>k</mi><mi>x</mi></mrow></msup><mo> </mo><mo> </mo><mfenced><mrow><mo>=</mo><msup><mtext>e</mtext><mrow><mi>k</mi><mi>x</mi></mrow></msup><mfenced><mrow><mn>2</mn><mi>k</mi><mi>x</mi><mo>-</mo><mi>k</mi><mo>+</mo><mn>2</mn></mrow></mfenced></mrow></mfenced></math>            <em><strong>A1</strong></em></p>\n<p>correct working for one of (seen anywhere)            <em><strong>A1</strong></em></p>\n<p style=\"padding-left:30px;\"><math xmlns=\"http://www.w3.org/1998/Math/MathML\"><mfrac><mrow><mo>d</mo><mi>y</mi></mrow><mrow><mo>d</mo><mi>x</mi></mrow></mfrac></math> at <math xmlns=\"http://www.w3.org/1998/Math/MathML\"><mi>x</mi><mo>=</mo><mn>1</mn><mo>⇒</mo><mi>k</mi><msup><mtext>e</mtext><mi>k</mi></msup><mo>+</mo><mn>2</mn><msup><mtext>e</mtext><mi>k</mi></msup></math></p>\n<p style=\"padding-left:30px;\"><br/><strong>OR</strong></p>\n<p style=\"padding-left:30px;\">slope of tangent is <math xmlns=\"http://www.w3.org/1998/Math/MathML\"><mn>5</mn><msup><mtext>e</mtext><mi>k</mi></msup></math></p>\n<p><br/>their <math xmlns=\"http://www.w3.org/1998/Math/MathML\"><mfrac><mrow><mo>d</mo><mi>y</mi></mrow><mrow><mo>d</mo><mi>x</mi></mrow></mfrac></math> at <math xmlns=\"http://www.w3.org/1998/Math/MathML\"><mi>x</mi><mo>=</mo><mn>1</mn></math> equals the <em>slope</em> of <math xmlns=\"http://www.w3.org/1998/Math/MathML\"><mi>y</mi><mo>=</mo><mn>5</mn><msup><mtext>e</mtext><mi>k</mi></msup><mi>x</mi><mo> </mo><mo> </mo><mfenced><mrow><mo>=</mo><mn>5</mn><msup><mtext>e</mtext><mi>k</mi></msup></mrow></mfenced></math> (seen anywhere)           <em><strong>(M1)</strong></em></p>\n<p><math xmlns=\"http://www.w3.org/1998/Math/MathML\"><mi>k</mi><msup><mtext>e</mtext><mi>k</mi></msup><mo>+</mo><mn>2</mn><msup><mtext>e</mtext><mi>k</mi></msup><mo>=</mo><mn>5</mn><msup><mtext>e</mtext><mi>k</mi></msup></math></p>\n<p><math xmlns=\"http://www.w3.org/1998/Math/MathML\"><mi>k</mi><mo>=</mo><mn>3</mn></math>            <em><strong>A1</strong></em></p>\n<p> </p>\n<p><em><strong>[5 marks]</strong></em></p>\n</div>", "examiners_html": "<div class=\"question\">\n<p>The product rule was well recognised and used with 𝑥=1 properly substituted into this expression. Although the majority of the candidates tried equating the derivative to the slope of the tangent line, the slope of the tangent line was not correctly identified; many candidates incorrectly substituted 𝑥=1 into the tangent equation, thus finding the <em>y</em>-coordinate instead of the slope.</p>\n</div>"}