{"id": 14753, "source": "pestle", "subject": "biology", "course": null, "level": "SL", "paper": "1", "year": "2021", "session": "21M", "subtopic": "1-1-introduction-to-cells", "title": "21M.1.SL.TZ1.5", "topic_id": "1", "source_url": "https://pestle.pages.dev/app/", "question_html": "<div class=\"question\">\n<p>Which living structure is an exception to the cell theory?</p>\n<p>A. Striated muscle fibres</p>\n<p>B. A single-celled alga carrying out all of the functions of life</p>\n<p>C. The artificial synthesis of the organic molecule urea</p>\n<p>D. A multicellular organism with cells undertaking specialized roles</p>\n</div>", "solution_html": "<div class=\"question\">\n<p>A</p>\n</div>", "examiners_html": "<div class=\"question\">\n[N/A]\n</div>"}