{"id": 15195, "source": "pestle", "subject": "biology", "course": null, "level": "HL", "paper": "1", "year": "2020", "session": "20N", "subtopic": "9-3-growth-in-plants", "title": "20N.1.HL.TZ0.33", "topic_id": "9", "source_url": "https://pestle.pages.dev/app/", "question_html": "<div class=\"question\">\n<p>How does auxin exert its effect on plant cells?</p>\n<p>A. Acts directly on the cell wall, causing expansion</p>\n<p>B. Binds to a receptor resulting in expression of genes</p>\n<p>C. Causes the vacuole to absorb water and expand the cell</p>\n<p>D. Causes the cell to undergo cell division</p>\n</div>", "solution_html": "<div class=\"question\">\n<p>B</p>\n</div>", "examiners_html": "<div class=\"question\">\n<p>Only 42 % of candidates were able to pick out how auxin exerts its effects on plant cells and all the four answers attracted significant numbers of candidates, suggesting a widespread lack of knowledge of this aspect of plant physiology.</p>\n</div>"}