{"id": 15381, "source": "pestle", "subject": "biology", "course": null, "level": "SL", "paper": "1", "year": "2020", "session": "20N", "subtopic": "4-3-carbon-cycling", "title": "20N.1.SL.TZ0.18", "topic_id": "4", "source_url": "https://pestle.pages.dev/app/", "question_html": "<div class=\"question\">\n<p>Under certain conditions, living organisms on Earth produce and release methane. What favours the production of methane?</p>\n<p>A. Forest fires</p>\n<p>B. High light intensity</p>\n<p>C. Anaerobic conditions</p>\n<p>D. Dry conditions</p>\n</div>", "solution_html": "<div class=\"question\">\n<p>C</p>\n</div>", "examiners_html": "<div class=\"question\">\n[N/A]\n</div>"}