{"id": 2202, "source": "pestle", "subject": "physics", "course": null, "level": "SL", "paper": "3", "year": "2017", "session": "17M", "subtopic": "d-3-cosmology, d-2-stellar-characteristics-and-stellar-evolution", "title": "17M.3.SL.TZ1.10", "topic_id": "d", "source_url": "https://pestle.pages.dev/app/", "question_html": "<div class=\"specification\">\n<p>A spectral line in the light received from a distant galaxy shows a redshift of <em>z</em> = 0.16.</p>\n</div><div class=\"question\" style=\"padding-left: 20px; padding-right: 20px;\">\n<p>State <strong>two</strong> characteristics of the cosmic microwave background (CMB) radiation.</p>\n<div class=\"marks\">[2]</div>\n<div class=\"question_part_label\">a.i.</div>\n</div><div class=\"question\" style=\"padding-left: 20px; padding-right: 20px;\">\n<p>The present temperature of the CMB is 2.8 K. Calculate the peak wavelength of the CMB.</p>\n<div class=\"marks\">[1]</div>\n<div class=\"question_part_label\">a.ii.</div>\n</div><div class=\"question\" style=\"padding-left: 20px; padding-right: 20px;\">\n<p>Describe how the CMB provides evidence for the Hot Big Bang model of the universe.</p>\n<div class=\"marks\">[2]</div>\n<div class=\"question_part_label\">b.</div>\n</div><div class=\"question\" style=\"padding-left: 20px; padding-right: 20px;\">\n<p>Determine the distance to this galaxy using a value for the Hubble constant of H<sub>0</sub> = 68 km s<sup>–1</sup><span class=\"mjpage\"><math alttext=\"\\,\" xmlns=\"http://www.w3.org/1998/Math/MathML\">\n<mspace width=\"thinmathspace\"></mspace>\n</math></span>Mpc<sup>–1</sup>.</p>\n<div class=\"marks\">[2]</div>\n<div class=\"question_part_label\">c.i.</div>\n</div><div class=\"question\" style=\"padding-left: 20px; padding-right: 20px;\">\n<p>Estimate the size of the Universe relative to its present size when the light was emitted by the galaxy in (c).</p>\n<div class=\"marks\">[2]</div>\n<div class=\"question_part_label\">c.ii.</div>\n</div>", "solution_html": "<div class=\"question\" style=\"padding-left: 20px;\">\n<p>black body radiation / 3 K</p>\n<p>highly isotropic / uniform throughout<br/><em><strong>OR</strong></em><br/>filling the universe</p>\n<p> </p>\n<p><em>Do not accept: CMB provides evidence for the Big Bang model.</em></p>\n<p><strong><em>[2 marks]</em></strong></p>\n<div class=\"question_part_label\">a.i.</div>\n</div><div class=\"question\" style=\"padding-left: 20px;\">\n<p>«<span class=\"mjpage\"><math alttext=\"\\lambda  = \\frac{{2.9 \\times {{10}^{ - 3}}}}{{2.8}}\" xmlns=\"http://www.w3.org/1998/Math/MathML\">\n<mi>λ</mi>\n<mo>=</mo>\n<mfrac>\n<mrow>\n<mn>2.9</mn>\n<mo>×</mo>\n<mrow>\n<msup>\n<mrow>\n<mn>10</mn>\n</mrow>\n<mrow>\n<mo>−</mo>\n<mn>3</mn>\n</mrow>\n</msup>\n</mrow>\n</mrow>\n<mrow>\n<mn>2.8</mn>\n</mrow>\n</mfrac>\n</math></span>» ≈ 1.0 «mm»</p>\n<p><em><strong>[1 mark]</strong></em></p>\n<div class=\"question_part_label\">a.ii.</div>\n</div><div class=\"question\" style=\"padding-left: 20px;\">\n<p>the universe is <strong>expanding</strong> and so the wavelength of the CMB in the past was much smaller</p>\n<p>indicating a very high temperature at the beginning</p>\n<p><em><strong>[2 marks]</strong></em></p>\n<div class=\"question_part_label\">b.</div>\n</div><div class=\"question\" style=\"padding-left: 20px;\">\n<p>«<span class=\"mjpage\"><math alttext=\"z = \\frac{v}{c} \\Rightarrow \" xmlns=\"http://www.w3.org/1998/Math/MathML\">\n<mi>z</mi>\n<mo>=</mo>\n<mfrac>\n<mi>v</mi>\n<mi>c</mi>\n</mfrac>\n<mo stretchy=\"false\">⇒</mo>\n</math></span>» <em>v</em> = 0.16 × 3 × 10<sup>5 </sup>«= 0.48 × 10<sup>5 </sup>km<span class=\"mjpage\"><math alttext=\"\\,\" xmlns=\"http://www.w3.org/1998/Math/MathML\">\n<mspace width=\"thinmathspace\"></mspace>\n</math></span>s<sup>−1</sup>»</p>\n<p>«<span class=\"mjpage\"><math alttext=\"d = \\frac{v}{{{H_0}}} \\Rightarrow v = \\frac{{0.48 \\times {{10}^5}}}{{68}} = 706\" xmlns=\"http://www.w3.org/1998/Math/MathML\">\n<mi>d</mi>\n<mo>=</mo>\n<mfrac>\n<mi>v</mi>\n<mrow>\n<mrow>\n<msub>\n<mi>H</mi>\n<mn>0</mn>\n</msub>\n</mrow>\n</mrow>\n</mfrac>\n<mo stretchy=\"false\">⇒</mo>\n<mi>v</mi>\n<mo>=</mo>\n<mfrac>\n<mrow>\n<mn>0.48</mn>\n<mo>×</mo>\n<mrow>\n<msup>\n<mrow>\n<mn>10</mn>\n</mrow>\n<mn>5</mn>\n</msup>\n</mrow>\n</mrow>\n<mrow>\n<mn>68</mn>\n</mrow>\n</mfrac>\n<mo>=</mo>\n<mn>706</mn>\n</math></span>» ≈ 710 «Mpc»</p>\n<p> </p>\n<p><em>Award <strong>[1 max]</strong> for POT error.</em></p>\n<p><strong><em>[2 marks]</em></strong></p>\n<div class=\"question_part_label\">c.i.</div>\n</div><div class=\"question\" style=\"padding-left: 20px;\">\n<p><span class=\"mjpage\"><math alttext=\"z = \\frac{R}{{{R_0}}} - 1 \\Rightarrow \\frac{R}{{{R_0}}} = 1.16\" xmlns=\"http://www.w3.org/1998/Math/MathML\">\n<mi>z</mi>\n<mo>=</mo>\n<mfrac>\n<mi>R</mi>\n<mrow>\n<mrow>\n<msub>\n<mi>R</mi>\n<mn>0</mn>\n</msub>\n</mrow>\n</mrow>\n</mfrac>\n<mo>−</mo>\n<mn>1</mn>\n<mo stretchy=\"false\">⇒</mo>\n<mfrac>\n<mi>R</mi>\n<mrow>\n<mrow>\n<msub>\n<mi>R</mi>\n<mn>0</mn>\n</msub>\n</mrow>\n</mrow>\n</mfrac>\n<mo>=</mo>\n<mn>1.16</mn>\n</math></span></p>\n<p><span class=\"mjpage\"><math alttext=\"\\frac{{{R_0}}}{R} = 0.86\" xmlns=\"http://www.w3.org/1998/Math/MathML\">\n<mfrac>\n<mrow>\n<mrow>\n<msub>\n<mi>R</mi>\n<mn>0</mn>\n</msub>\n</mrow>\n</mrow>\n<mi>R</mi>\n</mfrac>\n<mo>=</mo>\n<mn>0.86</mn>\n</math></span></p>\n<p><em><strong>[2 marks]</strong></em></p>\n<div class=\"question_part_label\">c.ii.</div>\n</div>", "examiners_html": "<div class=\"question\" style=\"padding-left: 20px;\">\n[N/A]\n<div class=\"question_part_label\">a.i.</div>\n</div><div class=\"question\" style=\"padding-left: 20px;\">\n[N/A]\n<div class=\"question_part_label\">a.ii.</div>\n</div><div class=\"question\" style=\"padding-left: 20px;\">\n[N/A]\n<div class=\"question_part_label\">b.</div>\n</div><div class=\"question\" style=\"padding-left: 20px;\">\n[N/A]\n<div class=\"question_part_label\">c.i.</div>\n</div><div class=\"question\" style=\"padding-left: 20px;\">\n[N/A]\n<div class=\"question_part_label\">c.ii.</div>\n</div>"}