{"id": 31040, "source": "pestle", "subject": "psychology", "course": null, "level": null, "paper": null, "year": null, "session": null, "subtopic": "violence", "title": "17N.2.BP.TZ0.12", "topic_id": "8", "source_url": "https://pestle.pages.dev/app/", "question_html": "<div class=\"question\">\n<p>Evaluate <strong>one or more</strong> sociocultural explanations of the origins of violence.</p>\n</div>", "solution_html": "<div class=\"question\">\n<p><em>Refer to the paper 2 assessment criteria when awarding marks.</em></p>\n<p><br/>The command term “evaluate” requires candidates to make an appraisal by weighing up the strengths and limitations of one or more sociocultural explanations of the origins of violence. Although a discussion of both strengths and limitations is required, it does not have to be evenly balanced to gain high marks.</p>\n<p><br/>Explanations may include, but are not limited to:<br/>• social identity theory (for example, Maass, 2003)<br/>• social learning theory (for example, Bandura, 1961)<br/>• negative social schemas (for example, Bradshaw, 2004)<br/>• deindividuation (for example, Festinger, Pepitone and Newcomb, 1952)<br/>• social interaction approach (for example, Tedeschi and Felson, 1994)<br/>• subculture of violence theory/Culture of Honour (for example, Nisbett and Cohen,1996).</p>\n<p><br/>Evaluation of the sociocultural explanation(s) may include, but is not limited to:<br/>• cultural and/or gender considerations<br/>• application of the explanations<br/>• empirical findings that support or refute the explanation<br/>• comparison/contrast to other explanations.</p>\n<p><br/>Although the main focus of the response should be on sociocultural explanations, cognitive and biological explanations are acceptable in order to emphasize a strength or limitation of the explanation.</p>\n<p><br/>If a candidate discusses only strengths or only limitations, the response should be awarded up to a maximum of <strong>[5]</strong> for criterion B, critical thinking, and up to a maximum of <strong>[2]</strong> for criterion C, organization. Up to full marks may be awarded for criterion A, knowledge and comprehension.</p>\n<p><br/>Candidates may evaluate one sociocultural explanation of the origins of violence in order to demonstrate depth of knowledge, or may examine a larger number of sociocultural explanations of the origins of violence in order to demonstrate breadth of knowledge. Both approaches are equally acceptable.</p>\n</div>", "examiners_html": "<div class=\"question\">\n[N/A]\n</div>"}