{"id": 32380, "source": "pestle", "subject": "history", "course": null, "level": null, "paper": null, "year": null, "session": null, "subtopic": "12-china-and-korea-(1910-1950)", "title": "17N.3OP3.HL.TZ0.24", "topic_id": "5", "source_url": "https://pestle.pages.dev/app/", "question_html": "<div class=\"question\">\n<p>“Japanese rule of Korea had an entirely negative impact on Korea’s economy and society.” To what extent do you agree with this statement?<br/><br/><br/></p>\n</div>", "solution_html": "<div class=\"question\">\n<p>Candidates will offer a considered and balanced review of the statement that Japanese rule of Korea had an entirely negative impact on Korea’s economy and society. Candidates may agree, partly agree or disagree with the statement. The impact on economy and society must be clearly indicated but there does not need to be an equal focus on both. Candidates may refer to the annexation of Korea in 1910 and the changes that occurred in Korean society and economy following this. For impact on society candidates may discuss the ways Korean culture and language were undermined, particularly from the 1930s onwards with the policy of assimilation. Under this policy, Koreans were to regard themselves as Japanese and, any resistance to this, was brutally suppressed. Candidates may refer to economic impacts including land reform, industrialisation, the development of infrastructure and the conscription of Koreans into civilian labour during the Second World War.</p>\n</div>", "examiners_html": "<div class=\"question\">\n[N/A]\n</div>"}