{"id": 32490, "source": "pestle", "subject": "history", "course": null, "level": null, "paper": null, "year": null, "session": null, "subtopic": "7-challenges-to-traditional-east-asian-societies-(1700-1868)", "title": "17M.3OP3.HL.TZ0.14", "topic_id": "5", "source_url": "https://pestle.pages.dev/app/", "question_html": "<div class=\"question\">\n<p>Evaluate the reasons for the fall of the Tokugawa Shogunate in 1868.<br/><br/></p>\n</div>", "solution_html": "<div class=\"question\">\n<p>Candidates will appraise reasons for the fall of the Tokugawa Shogunate by weighing up the significance of long- and short-term factors. Candidates may adopt a chronological approach that outlines the nature of Tokugawa society prior to 1853 and then the consequences of the treaties and events between 1854 and 1868. Alternatively, candidates may choose a thematic approach and address aspects such as economic problems, the decline of the feudal system, the rise of the <em>tozama</em> clans, political challenges to the Shogunate and the impact of foreign demands. Some candidates may argue that reasons for the fall of the Tokugawa Shogunate were inherent while others may consider the catalyst of Perry’s arrival more significant.</p>\n</div>", "examiners_html": "<div class=\"question\">\n[N/A]\n</div>"}