{"id": 32955, "source": "pestle", "subject": "history", "course": null, "level": null, "paper": null, "year": null, "session": null, "subtopic": "16-developments-and-challenges-in-south-asia-after-1947", "title": "20N.3OP3.HL.TZ0.32", "topic_id": "5", "source_url": "https://pestle.pages.dev/app/", "question_html": "<div class=\"specification\">\n<p><strong>Section 16: Developments and challenges in South Asia after 1947</strong></p>\n</div><div class=\"question\">\n<p>Evaluate the political and economic developments in India under Indira Gandhi.<br/><br/></p>\n</div>", "solution_html": "<div class=\"question\">\n<p>The question requires that candidates make an appraisal of the political and economic developments under Indira Gandhi, weighing up the strengths and limitations or otherwise of each. Candidates may offer equal coverage of political and economic developments, or they may prioritize their evaluation of one of these aspects. However, both aspects will be a feature of the response. Candidates may refer to her socialist policies including the nationalization of banks and the coal mines, the Green Revolution and the Five-Year Plans. For political developments, they may refer to the splitting of the Congress, declaration of India as a nuclear state, the constitutional amendments, the Emergency, and the Twenty Point Programme as well as Operation Bluestar. Candidates may discuss the controversial nature of these events. Accusations against Indira Gandhi of malpractices in elections led to the formation of a grand opposition alliance, the <em>Janta Morcha</em>. Candidates’ opinions or conclusions will be presented clearly and supported by appropriate evidence.</p>\n</div>", "examiners_html": "<div class=\"question\">\n<p>The question required that candidates make an appraisal of the political and economic developments under Indira Gandhi, weighing up the strengths and limitations or otherwise of each. Candidates needed to include both political and economic developments and identify successes and failings of these policies.</p>\n</div>"}