{"id": 7067, "source": "pestle", "subject": "chemistry", "course": null, "level": "SL", "paper": "1", "year": "2017", "session": "17M", "subtopic": "8-4-strong-and-weak-acids-and-bases", "title": "17M.1.SL.TZ1.20", "topic_id": "8", "source_url": "https://pestle.pages.dev/app/", "question_html": "<div class=\"question\">\n<p>Which 1.0 mol<span class=\"mjpage\"><math alttext=\"\\,\" xmlns=\"http://www.w3.org/1998/Math/MathML\">\n<mspace width=\"thinmathspace\"></mspace>\n</math></span>dm<sup>–3</sup> solution has the highest pH?</p>\n<p>A.     Ammonium chloride</p>\n<p>B.     Sulfuric acid</p>\n<p>C.     Sodium chloride</p>\n<p>D.     Ammonia</p>\n</div>", "solution_html": "<div class=\"question\">\n<p>D</p>\n</div>", "examiners_html": "<div class=\"question\">\n[N/A]\n</div>"}