{"id": 8021, "source": "pestle", "subject": "chemistry", "course": null, "level": "HL", "paper": "1", "year": "2020", "session": "20N", "subtopic": "3-2-periodic-trends", "title": "20N.1.HL.TZ0.6", "topic_id": "3", "source_url": "https://pestle.pages.dev/app/", "question_html": "<div class=\"question\">\n<p><span class=\"fontstyle0\">What is the correct trend going down groups 1 </span><strong><span class=\"fontstyle2\">and </span></strong><span class=\"fontstyle0\">17?</span></p>\n<p><span class=\"fontstyle0\">A. Melting points increase<br/></span></p>\n<p><span class=\"fontstyle0\">B. Boiling points decrease<br/></span></p>\n<p><span class=\"fontstyle0\">C. Electronegativities increase<br/></span></p>\n<p><span class=\"fontstyle0\">D. Ionization energies decrease</span></p>\n</div>", "solution_html": "<div class=\"question\">\n<p>D</p>\n</div>", "examiners_html": "<div class=\"question\">\n<p>Most candidates selected ionization energy as the property that decreases down both group 1 and 17.</p>\n</div>"}