{"id": 8337, "source": "pestle", "subject": "chemistry", "course": null, "level": "SL", "paper": "1", "year": "2021", "session": "21N", "subtopic": "2-2-electron-configuration", "title": "21N.1.SL.TZ0.6", "topic_id": "2", "source_url": "https://pestle.pages.dev/app/", "question_html": "<div class=\"question\">\n<p>How many p-orbitals are occupied in a phosphorus atom?</p>\n<p><br/>A.  2</p>\n<p>B.  3</p>\n<p>C.  5</p>\n<p>D.  6</p>\n</div>", "solution_html": "<div class=\"question\">\n<p>D</p>\n</div>", "examiners_html": "<div class=\"question\">\n[N/A]\n</div>"}